sketch_preproc/__init__.py
sketch_preproc/common/__init__.py
sketch_preproc/common/config.py
sketch_preproc/common/edge_detection.py
sketch_preproc/common/io.py
sketch_preproc/common/utils.py
sketch_preproc/presets/default_v3.yml
sketch_preproc/presets/default_v4.yml
sketch_preproc/presets/spectrum_01_bare_bones.yml
sketch_preproc/presets/spectrum_01_bare_bones_v4.yml
sketch_preproc/presets/spectrum_02_minimal.yml
sketch_preproc/presets/spectrum_02_minimal_v4.yml
sketch_preproc/presets/spectrum_03_fine.yml
sketch_preproc/presets/spectrum_03_fine_v4.yml
sketch_preproc/presets/spectrum_04_balanced_fine.yml
sketch_preproc/presets/spectrum_04_balanced_fine_v4.yml
sketch_preproc/presets/spectrum_05_balanced.yml
sketch_preproc/presets/spectrum_05_balanced_v4.yml
sketch_preproc/presets/spectrum_06_balanced_detail.yml
sketch_preproc/presets/spectrum_06_balanced_detailed.yml
sketch_preproc/presets/spectrum_06_balanced_detailed_v4.yml
sketch_preproc/presets/spectrum_07_detailed.yml
sketch_preproc/presets/spectrum_07_detailed_v4.yml
sketch_preproc/presets/spectrum_08_very_detailed.yml
sketch_preproc/presets/spectrum_08_very_detailed_v4.yml
sketch_preproc/presets/spectrum_09_comprehensive.yml
sketch_preproc/presets/spectrum_09_comprehensive_v4.yml
sketch_preproc/presets/spectrum_10_maximal.yml
sketch_preproc/presets/spectrum_10_maximal_v4.yml
sketch_preproc/v3/__init__.py
sketch_preproc/v3/pipeline.py
sketch_preproc/v3/salience.py
sketch_preproc/v4/__init__.py
sketch_preproc/v4/pipeline.py
sketch_preproc/v4/preprocess.py
sketch_preproc/v4/salience.py
sketch_preproc-0.2.1.dist-info/METADATA
sketch_preproc-0.2.1.dist-info/WHEEL
sketch_preproc-0.2.1.dist-info/top_level.txt
sketch_preproc-0.2.1.dist-info/RECORD
