Metadata-Version: 2.4
Name: sketch-preproc
Version: 0.2.1
Summary: Sketch preprocessing pipelines with edge detection presets
Author: Sketch Preproc Team
License: MIT
Requires-Python: >=3.8
Requires-Dist: opencv-python>=4.10
Requires-Dist: opencv-contrib-python>=4.10
Requires-Dist: torch>=2.2
Requires-Dist: kornia>=0.7
Requires-Dist: scikit-image>=0.19
Requires-Dist: sknw
Requires-Dist: numpy>=1.20
Requires-Dist: scipy>=1.7
Requires-Dist: pyyaml>=6.0
Requires-Dist: pillow>=9.0
Requires-Dist: matplotlib>=3.5
Provides-Extra: dev
Requires-Dist: black>=23.0; extra == "dev"
Requires-Dist: flake8>=6.0; extra == "dev"
Requires-Dist: pytest>=7.0; extra == "dev"
Requires-Dist: pytest-cov>=4.0; extra == "dev"
